bigtiger/__init__.py
bigtiger/contrib/__init__.py
bigtiger/contrib/admin/__init__.py
bigtiger/contrib/admin/apps.py
bigtiger/contrib/admin/widgets.py
bigtiger/contrib/admin/forms/__init__.py
bigtiger/contrib/admin/static/My97DatePicker/README.md
bigtiger/contrib/admin/static/My97DatePicker/WdatePicker.js
bigtiger/contrib/admin/static/My97DatePicker/calendar.js
bigtiger/contrib/admin/static/My97DatePicker/lang/en.js
bigtiger/contrib/admin/static/My97DatePicker/lang/zh-cn.js
bigtiger/contrib/admin/static/My97DatePicker/lang/zh-tw.js
bigtiger/contrib/admin/static/My97DatePicker/skin/WdatePicker.css
bigtiger/contrib/admin/static/My97DatePicker/skin/datePicker.gif
bigtiger/contrib/admin/static/My97DatePicker/skin/default/datepicker.css
bigtiger/contrib/admin/static/My97DatePicker/skin/default/img.gif
bigtiger/contrib/admin/static/My97DatePicker/skin/whyGreen/bg.jpg
bigtiger/contrib/admin/static/My97DatePicker/skin/whyGreen/datepicker.css
bigtiger/contrib/admin/static/My97DatePicker/skin/whyGreen/img.gif
bigtiger/contrib/admin/static/My97DatePicker/开发包/readme.txt
bigtiger/contrib/admin/static/My97DatePicker/开发包/lang/en.js
bigtiger/contrib/admin/static/My97DatePicker/开发包/lang/zh-cn.js
bigtiger/contrib/admin/static/My97DatePicker/开发包/lang/zh-tw.js
bigtiger/contrib/admin/static/My97DatePicker/开发包/skin/WdatePicker.css
bigtiger/contrib/admin/static/My97DatePicker/开发包/skin/datePicker.gif
bigtiger/contrib/admin/static/My97DatePicker/开发包/skin/default/datepicker.css
bigtiger/contrib/admin/static/My97DatePicker/开发包/skin/default/img.gif
bigtiger/contrib/admin/static/My97DatePicker/开发包/skin/whyGreen/bg.jpg
bigtiger/contrib/admin/static/My97DatePicker/开发包/skin/whyGreen/datepicker.css
bigtiger/contrib/admin/static/My97DatePicker/开发包/skin/whyGreen/img.gif
bigtiger/contrib/admin/static/admin/fonts/glyphicons-halflings-regular.eot
bigtiger/contrib/admin/static/admin/fonts/glyphicons-halflings-regular.svg
bigtiger-0.3.8.dist-info/DESCRIPTION.rst
bigtiger-0.3.8.dist-info/METADATA
bigtiger-0.3.8.dist-info/RECORD
bigtiger-0.3.8.dist-info/WHEEL
bigtiger-0.3.8.dist-info/metadata.json
bigtiger-0.3.8.dist-info/top_level.txt
