Metadata-Version: 2.0
Name: bigtiger
Version: 0.3.8
Summary: similar django admin
Home-page: http://www.hshl.ltd
Author: bigtiger
Author-email: chinafengheping@gmail.com
License: UNKNOWN
Platform: UNKNOWN
Requires-Dist: Django (>=1.7.7)
Requires-Dist: djangorestframework (>=3.3.1)
Requires-Dist: djangorestframework-xml (>=1.3.0)
Requires-Dist: pycrypto (>=2.6.1)
Requires-Dist: sqlalchemy-django (>=0.0.4)
Requires-Dist: xlrd (>=0.9.3)
Requires-Dist: xlutils (>=1.7.1)
Requires-Dist: xlwt (>=0.7.5)
